LICENSE.md
MANIFEST.in
README.md
build_upload.md
pyproject.toml
setup.cfg
setup.py
src/selenium_interceptor/__init__.py
src/selenium_interceptor/interceptor.py
src/selenium_interceptor.egg-info/PKG-INFO
src/selenium_interceptor.egg-info/SOURCES.txt
src/selenium_interceptor.egg-info/dependency_links.txt
src/selenium_interceptor.egg-info/requires.txt
src/selenium_interceptor.egg-info/top_level.txt
src/selenium_interceptor/scripts/__init__.py
src/selenium_interceptor/scripts/multi_thread.py
src/selenium_interceptor/utils/__init__.py
src/selenium_interceptor/utils/utils.py
tests/test_interceptor.py