Metadata-Version: 2.1
Name: selenium-interceptor
Version: 1.0.2
Summary: Intercept requests using Selenium with Chrome
Home-page: https://github.com/kaliiiiiiiiii/selenium_interceptor
Author: Aurin Aegerter
Author-email: aurinliun@gmx.ch
Project-URL: Documentation, https://github.com/kaliiiiiiiiii/selenium_interceptor
Project-URL: Bug Reports, https://github.com/kaliiiiiiiiii/selenium_interceptor/issues
Project-URL: Source Code, https://github.com/kaliiiiiiiiii/selenium_interceptor
Keywords: Selenium,interception,proxy,webautomation
Classifier: Development Status :: 2 - Pre-Alpha
Classifier: Intended Audience :: Developers
Classifier: Programming Language :: Python :: 3
Classifier: Programming Language :: Python :: 3.7
Classifier: Programming Language :: Python :: 3.8
Classifier: Programming Language :: Python :: 3.9
Classifier: Programming Language :: Python :: 3.10
Classifier: Programming Language :: Python :: 3.11
Classifier: License :: Free for non-commercial use
Classifier: Natural Language :: English
Classifier: Operating System :: OS Independent
Classifier: Topic :: Internet :: Proxy Servers
Classifier: Topic :: Internet
Classifier: Topic :: Internet :: WWW/HTTP :: Browsers
Requires-Python: >=3.7
Provides-Extra: dev
License-File: LICENSE.md
